.gitignore
README.md
requirements.txt
setup.py
cli_todo_app.egg-info/PKG-INFO
cli_todo_app.egg-info/SOURCES.txt
cli_todo_app.egg-info/dependency_links.txt
cli_todo_app.egg-info/requires.txt
cli_todo_app.egg-info/top_level.txt
todo/__init__.py
todo/cli_todo_app.py