Metadata-Version: 2.1
Name: cli-todo-app
Version: 1.0.0
Summary: CLI application for saving todos.
Author: Sheikh Hafijul Ali
Author-email: hafijul.dev@gmail.com
Classifier: Programming Language :: Python :: 3
Classifier: Operating System :: OS Independent
Requires-Python: >=3.6
